setup.py
logModel.egg-info/PKG-INFO
logModel.egg-info/SOURCES.txt
logModel.egg-info/dependency_links.txt
logModel.egg-info/top_level.txt
log_model/__init__.py
log_model/get_logger.py